store/ALU.v
module ALU (
    input [31:0] a, b,
    input [2:0] alu_control,
    output reg [31:0] result,
    output zero
);
    always @(*) begin
        case (alu_control)
            3'b000: result = a & b;
            3'b001: result = a | b;
            3'b010: result = a + b;
            3'b011: result = a - b;
            3'b100: result = a < b;
            default: result = 32'b0;
        endcase
    end

    assign zero = (result == 0); 
    //result checker if zero
endmodule

Storing/ALU_tb.v
`timescale 1ns/1ns
`include "ALU.v"

module alu_tb ();
    
    //inputs and outputs(reg/wire)
    reg [31:0] a, b;
    reg [2:0] alu_control;

    wire [31:0] result;
    wire zero;

    //unit under test alu
    ALU uut(
        .a(a),
        .b(b),
        .alu_control(alu_control),
        .result(result),
        .zero(zero)
    );

    //Test
    initial begin
        $dumpfile("ALU_tb.vcd"); //output file that holds the waveform
        $dumpvars(0, alu_tb); //variables dumped at time 0
        //Test operations here
        //Test For AND Waves


        a = 1;
        b = 1;
        alu_control = 3'b000; // AND
        #20;

        a = 1;
        b = 0;
        alu_control = 3'b000; // AND
        #20;

        $display("Result of AND (1,0): %d", result);

        a = 1;
        b = 1;
        alu_control = 3'b001; // OR
        #20;

        a = 1;
        b = 0;
        alu_control = 3'b001; // OR
        #20;
        $display("Result of OR (1,0): %d", result);

        a = 1;
        b = 1;
        alu_control = 3'b010; // ADD
        #20;

        a = 1;
        b = 0;
        alu_control = 3'b010; // ADD
        #20;
        $display("Result of ADD (1,0): %d", result);

        a = 1;
        b = 1;
        alu_control = 3'b011; // SUB
        #20;

        a = 1;
        b = 0;
        alu_control = 3'b011; // SUB
        #20;
        $display("Result of SUB (1,0): %d", result);

        a = 1;
        b = 1;
        alu_control = 3'b100; // SLT
        #20;

        a = 1;
        b = 0;
        alu_control = 3'b100; // SLT
        #20;
        $display("Result of SLT (1,0): %d", result);
    end

endmodule

Storing/ALU_tb.vcd
$date
	Sat May 11 03:55:42 2024
$end
$version
	Icarus Verilog
$end
$timescale
	1ns
$end
$scope module alu_tb $end
$var wire 1 ! zero $end
$var wire 32 " result [31:0] $end
$var reg 32 # a [31:0] $end
$var reg 3 $ alu_control [2:0] $end
$var reg 32 % b [31:0] $end
$scope module uut $end
$var wire 32 & a [31:0] $end
$var wire 3 ' alu_control [2:0] $end
$var wire 32 ( b [31:0] $end
$var wire 1 ! zero $end
$var reg 32 ) result [31:0] $end
$upscope $end
$upscope $end
$enddefinitions $end
#0
$dumpvars
b1 )
b1 (
b0 '
b1 &
b1 %
b0 $
b1 #
b1 "
0!
$end
#20
1!
b0 "
b0 )
b0 %
b0 (
#40
0!
b1 "
b1 )
b1 $
b1 '
b1 %
b1 (
#60
b0 %
b0 (
#80
b10 "
b10 )
b10 $
b10 '
b1 %
b1 (
#100
b1 "
b1 )
b0 %
b0 (
#120
1!
b0 "
b0 )
b11 $
b11 '
b1 %
b1 (
#140
0!
b1 "
b1 )
b0 %
b0 (
#160
1!
b0 "
b0 )
b100 $
b100 '
b1 %
b1 (
#180
b0 %
b0 (
