Storing/RegisterFile.v

module RegisterFile(
	input reset,
	input clk,
	input [31:0] Read_register1,
	input [31:0] Read_register2,
	output reg [31:0] Read_data1,
	output reg [31:0] Read_data2
	);

	reg [31:0] RF_data[31:1]; //array that stores 31 registers
	
	integer i;
	always @(posedge reset or posedge clk)
		if (reset) begin
			
			RF_data [1] = 32'h11111111;
			RF_data [2] = 32'h22222222;
			RF_data [3] = 32'h33333333;
			RF_data [4] = 32'h44444444;
			RF_data [5] = 32'h55555555;
			RF_data [6] = 32'h66666666;
			RF_data [7] = 32'h77777777;
			RF_data [8] = 32'h88888888;
			RF_data [9] = 32'h99999999;
			RF_data [10] = 32'hAAAAAAAA;
			RF_data [11] = 32'hBBBBBBBB;
			RF_data [12] = 32'hCCCCCCCC;
			RF_data [13] = 32'hDDDDDDDD;
			RF_data [14] = 32'hEEEEEEEE;
			RF_data [15] = 32'hFFFFFFFF;
			RF_data [16] = 32'h11111111;
			RF_data [17] = 32'h22222222;
			RF_data [18] = 32'h33333333;
			RF_data [19] = 32'h44444444;
			RF_data [20] = 32'h55555555;
			RF_data [21] = 32'h66666666;
			RF_data [22] = 32'h77777777;
			RF_data [23] = 32'h88888888;
			RF_data [24] = 32'h99999999;
			RF_data [25] = 32'hAAAAAAAA;
			RF_data [26] = 32'hBBBBBBBB;
			RF_data [27] = 32'hCCCCCCCC;
			RF_data [28] = 32'hDDDDDDDD;
			RF_data [29] = 32'hEEEEEEEE;
			RF_data [30] = 32'hFFFFFFFF;
			RF_data [31] = 32'h00000000;

		end else begin 
			Read_data1 <= (Read_register1 == 32'h00000000)? 32'h00000000: RF_data[Read_register1];
			Read_data2 <= (Read_register2 == 32'h00000000)? 32'h00000000: RF_data[Read_register2];
		end


endmodule

Storing/RegisterFile_tb.v
`include "RegisterFile.v"
`timescale 1ps/1ps

module RegisterFile_tb();

    // Parameters
    parameter CLK_PERIOD = 10; // Clock period in time units

    // Inputs
    reg reset, clk;
    reg [31:0] Read_register1, Read_register2;

    // Outputs
    wire [31:0] Read_data1, Read_data2;

    // Instantiate the module under test
    RegisterFile uut (
        .reset(reset),
        .clk(clk),
        .Read_register1(Read_register1),
        .Read_register2(Read_register2),
        .Read_data1(Read_data1),
        .Read_data2(Read_data2)
    );

    // Clock generation
    always #(CLK_PERIOD) clk = ~clk;

    // Test stimuli
    initial begin
        $dumpfile("RegisterFile_tb.vcd");
        $dumpvars(0, RegisterFile_tb);

        // Initialize inputs
        reset = 1;
        clk = 0;
        Read_register1 = 5'b00000;
        Read_register2 = 5'b00000;

        #20 
        reset = 0; // De-assert reset

        #20

        // Read from register 5
        Read_register1 = 5'b00101;
        Read_register2 = 5'b00000;

        #20
        // Read from register 10 and 5
        Read_register1 = 5'b01010;
        Read_register2 = 5'b00101;

        #20
   
      
        // Read from register 15 and 10
        Read_register1 = 5'b01111;
        Read_register2 = 5'b01010;

        #20
        
        // Read from register 20 and 15
        Read_register1 = 5'b10100;
        Read_register2 = 5'b01111;
        #20


        $finish;
    end

endmodule

Storing/RegisterFile_tb.vcd
$date
	Sat May 11 04:20:06 2024
$end
$version
	Icarus Verilog
$end
$timescale
	1ps
$end
$scope module RegisterFile_tb $end
$var wire 32 ! Read_data2 [31:0] $end
$var wire 32 " Read_data1 [31:0] $end
$var reg 32 # Read_register1 [31:0] $end
$var reg 32 $ Read_register2 [31:0] $end
$var reg 1 % clk $end
$var reg 1 & reset $end
$scope module uut $end
$var wire 32 ' Read_register1 [31:0] $end
$var wire 32 ( Read_register2 [31:0] $end
$var wire 1 % clk $end
$var wire 1 & reset $end
$var reg 32 ) Read_data1 [31:0] $end
$var reg 32 * Read_data2 [31:0] $end
$upscope $end
$upscope $end
$enddefinitions $end
#0
$dumpvars
bx *
bx )
b0 (
b0 '
1&
0%
b0 $
b0 #
bx "
bx !
$end
#10
1%
#20
0%
0&
#30
b0 !
b0 *
b0 "
b0 )
1%
#40
0%
b101 #
b101 '
#50
b1010101010101010101010101010101 "
b1010101010101010101010101010101 )
1%
#60
0%
b101 $
b101 (
b1010 #
b1010 '
#70
b1010101010101010101010101010101 !
b1010101010101010101010101010101 *
b10101010101010101010101010101010 "
b10101010101010101010101010101010 )
1%
#80
0%
b1010 $
b1010 (
b1111 #
b1111 '
#90
b10101010101010101010101010101010 !
b10101010101010101010101010101010 *
b11111111111111111111111111111111 "
b11111111111111111111111111111111 )
1%
#100
0%
b1111 $
b1111 (
b10100 #
b10100 '
#110
b11111111111111111111111111111111 !
b11111111111111111111111111111111 *
b1010101010101010101010101010101 "
b1010101010101010101010101010101 )
1%
